setup.cfg
setup.py
pydataportability/__init__.py
pydataportability.microformats.hcard.egg-info/PKG-INFO
pydataportability.microformats.hcard.egg-info/SOURCES.txt
pydataportability.microformats.hcard.egg-info/dependency_links.txt
pydataportability.microformats.hcard.egg-info/entry_points.txt
pydataportability.microformats.hcard.egg-info/namespace_packages.txt
pydataportability.microformats.hcard.egg-info/not-zip-safe
pydataportability.microformats.hcard.egg-info/paster_plugins.txt
pydataportability.microformats.hcard.egg-info/requires.txt
pydataportability.microformats.hcard.egg-info/top_level.txt
pydataportability/microformats/__init__.py
pydataportability/microformats/hcard/__init__.py
pydataportability/microformats/hcard/parser.py
pydataportability/microformats/hcard/tests/__init__.py
pydataportability/microformats/hcard/tests/doctests.py
pydataportability/microformats/hcard/tests/parsing.txt
pydataportability/microformats/hcard/tests/testfiles.py
