Metadata-Version: 1.0
Name: pydataportability.microformats.hcard
Version: 0.1dev-r25
Summary: an hCard parser
Home-page: http://mrtopf.de/blog
Author: Christian Scholz
Author-email: cs@comlounge.net
License: LGPL
Keywords: microformats parser hcard vcard dataportability
Platform: UNKNOWN
Classifier: Framework :: Plone
Classifier: Framework :: Zope2
Classifier: Framework :: Zope3
Classifier: Programming Language :: Python
Classifier: Topic :: Software Development :: Libraries :: Python Modules
